ruled_password_generator.py
ruled_password_generator-1.0.1.dist-info/LICENSE
ruled_password_generator-1.0.1.dist-info/METADATA
ruled_password_generator-1.0.1.dist-info/WHEEL
ruled_password_generator-1.0.1.dist-info/top_level.txt
ruled_password_generator-1.0.1.dist-info/RECORD
