Metadata-Version: 2.1
Name: ruled-password-generator
Version: 1.0.1
Summary: Password generator with customizable rules.
Home-page: https://github.com/hkcomori/ruled-password-generator
Author: hkcomori
Author-email: hkcomori@gmail.com
License: MIT
Platform: UNKNOWN
Classifier: License :: OSI Approved :: MIT License
Classifier: Programming Language :: Python
Classifier: Programming Language :: Python :: 3.7
Classifier: Programming Language :: Python :: 3.8
Classifier: Programming Language :: Python :: 3.9
Classifier: Programming Language :: Python :: 3.10
Classifier: Topic :: Security
Classifier: Topic :: Software Development :: Libraries :: Python Modules
Requires-Python: >=3.7
Provides-Extra: cpu
Provides-Extra: gpu
